neoclima/__init__.py
neoclima/__main__.py
neoclima/main.py
neoclima-1.0.10.dist-info/LICENSE
neoclima-1.0.10.dist-info/METADATA
neoclima-1.0.10.dist-info/WHEEL
neoclima-1.0.10.dist-info/entry_points.txt
neoclima-1.0.10.dist-info/RECORD
