Metadata-Version: 2.1
Name: neoclima
Version: 1.0.10
Summary: Modern CLI Weather App
Author: caiopeternela
Author-email: caiopeternela.dev@gmail.com
Requires-Python: >=3.8,<4.0
Classifier: Programming Language :: Python :: 3
Classifier: Programming Language :: Python :: 3.8
Classifier: Programming Language :: Python :: 3.9
Classifier: Programming Language :: Python :: 3.10
Classifier: Programming Language :: Python :: 3.11
Requires-Dist: requests (>=2.28.1,<3.0.0)
Requires-Dist: tinydb (>=4.7.0,<5.0.0)
Requires-Dist: typer[all] (>=0.7.0,<0.8.0)
